{
  "node": {
    "00b7a57c14b2684975b2c912dfa8f62e85d5d7f389": {
      "workers": {
        "app/activities/[id]/posts/new/page": {
          "moduleId": "6652",
          "async": false,
          "exportedName": "logoutUser",
          "filename": "src/actions/userLogout.ts"
        }
      },
      "layer": {
        "app/activities/[id]/posts/new/page": "action-browser"
      },
      "exportedName": "logoutUser",
      "filename": "src/actions/userLogout.ts"
    },
    "7008b151044865d41949dee997c4a21031a45bff04": {
      "workers": {
        "app/activities/[id]/posts/new/page": {
          "moduleId": "6652",
          "async": false,
          "exportedName": "createPost",
          "filename": "src/actions/createPost.ts"
        }
      },
      "layer": {
        "app/activities/[id]/posts/new/page": "action-browser"
      },
      "exportedName": "createPost",
      "filename": "src/actions/createPost.ts"
    }
  },
  "edge": {}
}